grabpayclient/__init__.py
grabpayclient/client.py
grabpayclient/common.py
grabpayclient/helper.py
grabpayclient/requests.py
grabpayclient/responses.py
GrabPay_Client-0.0.1.dist-info/LICENSE
GrabPay_Client-0.0.1.dist-info/METADATA
GrabPay_Client-0.0.1.dist-info/WHEEL
GrabPay_Client-0.0.1.dist-info/top_level.txt
GrabPay_Client-0.0.1.dist-info/RECORD
