Metadata-Version: 2.1
Name: GrabPay-Client
Version: 0.0.1
Summary: GrabPay Client Package
Home-page: https://github.com/yosephoche/grabpay-client
Author: ocDev
Author-email: yosephoche@gmail.com
License: UNKNOWN
Project-URL: Bug Tracker, https://github.com/yosephoche/grabpay-client/issues
Platform: UNKNOWN
Classifier: Programming Language :: Python :: 3
Classifier: License :: OSI Approved :: MIT License
Classifier: Operating System :: OS Independent
Requires-Python: >=3.6
License-File: LICENSE
